tox_delay/__init__.py
tox_delay/__main__.py
tox_delay/py.typed
tox_delay-0.1.3.dist-info/METADATA
tox_delay-0.1.3.dist-info/WHEEL
tox_delay-0.1.3.dist-info/entry_points.txt
tox_delay-0.1.3.dist-info/top_level.txt
tox_delay-0.1.3.dist-info/zip-safe
tox_delay-0.1.3.dist-info/RECORD
